mwot/__init__.py
mwot/__main__.py
mwot/compiler.py
mwot/join.py
mwot/stypes.py
mwot/util.py
mwot/binary/__init__.py
mwot/brainfuck/__init__.py
mwot/brainfuck/interpreter.py
mwot/cli/__init__.py
mwot/cli/actions.py
mwot/cli/argtypes.py
mwot/cli/parsing.py
mwot/cli/sources.py
mwot/decompilers/__init__.py
mwot/decompilers/basic.py
mwot/decompilers/common.py
mwot/decompilers/guide.py
mwot/decompilers/rand.py
mwot-0.1.1.dist-info/METADATA
mwot-0.1.1.dist-info/UNLICENSE
mwot-0.1.1.dist-info/WHEEL
mwot-0.1.1.dist-info/entry_points.txt
mwot-0.1.1.dist-info/top_level.txt
mwot-0.1.1.dist-info/RECORD
