Metadata-Version: 2.1
Name: mwot
Version: 0.1.1
Summary: Constrained writing as an encoding
Home-page: https://codeberg.org/gramkraxor/mwot
Author: Gramkraxor
Author-email: gram@krax.dev
License: Unlicense
Keywords: esolang,esoteric language,brainfuck
Classifier: License :: OSI Approved :: The Unlicense (Unlicense)
Classifier: Operating System :: OS Independent
Classifier: Programming Language :: Python :: 3
Classifier: Programming Language :: Python :: 3 :: Only
Classifier: Programming Language :: Python :: 3.8
Classifier: Programming Language :: Python :: 3.9
Classifier: Programming Language :: Python :: 3.10
Classifier: Topic :: Software Development :: Compilers
Classifier: Topic :: Software Development :: Interpreters
Requires-Python: >=3.8
License-File: UNLICENSE
